pyops/__init__.py
pyops/__version__.py
pyops/core.py
pyops-0.0.2.dist-info/LICENSE
pyops-0.0.2.dist-info/METADATA
pyops-0.0.2.dist-info/WHEEL
pyops-0.0.2.dist-info/top_level.txt
pyops-0.0.2.dist-info/RECORD
