Metadata-Version: 2.1
Name: pyops
Version: 0.0.2
Summary: OpenSearch python client.
Home-page: https://github.com/devsf/pyops
Author: Sergio Ferraresi
Author-email: dev@sergioferraresi.it
License: Apache2.0
Keywords: opensearch geo search
Platform: UNKNOWN
Classifier: Development Status :: 5 - Production/Stable
Classifier: Intended Audience :: Developers
Classifier: License :: OSI Approved :: Apache Software License
Classifier: Programming Language :: Python
Classifier: Programming Language :: Python :: 2
Classifier: Programming Language :: Python :: 2.7
Classifier: Programming Language :: Python :: 3
Classifier: Programming Language :: Python :: 3.4
Classifier: Programming Language :: Python :: 3.5
Classifier: Programming Language :: Python :: 3.6
Classifier: Programming Language :: Python :: 3.7
Classifier: Operating System :: OS Independent
Requires-Python: >=2.7.0
Requires-Dist: requests
